{
  "Id": 82,
  "MinecraftId": "minecraft:clay",
  "Subtypes": [
    {
      "Id": 0,
      "StringId": "clay",
      "Hardness": 0.6000000238418579,
      "BlastResistance": 3.0,
      "isSolid": true,
      "TileEntityClass": null,
      "LiquidSettings": {
        "IsLiquid": false,
        "SpillRadius": {}
      },
      "LightSettings": {
        "EmitLight": 0,
        "FilterLight": 15
      },
      "FlameableSettings": {
        "canBeSetOnFire": true,
        "BurnChances": 0.0,
        "FlameChances": 0.0
      },
      "DisplayNameKey": "clay.clay",
      "States": []
    }
  ],
  "DefaultSubtype": "clay"
}

