{
  "Id": 138,
  "MinecraftId": "minecraft:beacon",
  "Subtypes": [
    {
      "Id": 0,
      "StringId": "beacon",
      "Hardness": 3.0,
      "BlastResistance": 15.0,
      "isSolid": true,
      "TileEntityClass": null,
      "LiquidSettings": {
        "IsLiquid": false,
        "SpillRadius": {}
      },
      "LightSettings": {
        "EmitLight": 0,
        "FilterLight": 15
      },
      "FlameableSettings": {
        "canBeSetOnFire": true,
        "BurnChances": 0.0,
        "FlameChances": 0.0
      },
      "DisplayNameKey": "beacon.beacon",
      "States": []
    }
  ],
  "DefaultSubtype": "beacon"
}

