{
  "Id": 122,
  "MinecraftId": "minecraft:dragon_egg",
  "Subtypes": [
    {
      "Id": 0,
      "StringId": "dragon_egg",
      "Hardness": 3.0,
      "BlastResistance": 45.0,
      "isSolid": true,
      "TileEntityClass": null,
      "LiquidSettings": {
        "IsLiquid": false,
        "SpillRadius": {}
      },
      "LightSettings": {
        "EmitLight": 0,
        "FilterLight": 15
      },
      "FlameableSettings": {
        "canBeSetOnFire": true,
        "BurnChances": 0.0,
        "FlameChances": 0.0
      },
      "DisplayNameKey": "dragon_egg.dragon_egg",
      "States": []
    }
  ],
  "DefaultSubtype": "dragon_egg"
}

